{"skeleton":{"hash":"9ZEXMxsKun7dkfVVVaIaqCgnKnQ","spine":"3.1.08","width":163.3,"height":121.64,"images":"./images/"},"bones":[{"name":"root"},{"name":"bone","parent":"root","x":-3.42,"y":17.26},{"name":"bone2","parent":"bone","x":83.87,"y":-3.56,"scaleY":0.668},{"name":"gou1","parent":"bone2","x":-71.49,"y":-0.78},{"name":"gou2","parent":"bone","x":20.39,"y":-30.41,"scaleX":1.731,"scaleY":1.731},{"name":"gou3","parent":"bone","x":-41.28,"y":14.04,"scaleX":1.4,"scaleY":1.4,"rotation":35.99},{"name":"huaizi","parent":"bone","length":140.03,"x":-54.64,"y":-43.88,"rotation":36.87},{"name":"huai1","parent":"huaizi","length":16.46,"x":115.23,"y":5.24,"rotation":-32.36},{"name":"huai2","parent":"huaizi","length":10.37,"x":137.27,"y":15.18,"rotation":-35.68},{"name":"huai3","parent":"huaizi","length":11.32,"x":125.77,"y":-53.6,"rotation":51.08},{"name":"huai4","parent":"huaizi","length":12.96,"x":78.26,"y":-41.29,"rotation":-65.68},{"name":"huai6","parent":"huaizi","length":11.93,"x":115.15,"y":10.17,"rotation":174.81},{"name":"huai7","parent":"huaizi","length":13.87,"x":101.32,"y":28.95,"rotation":57.6},{"name":"huai8","parent":"huaizi","length":10.9,"x":90.91,"y":27.53,"rotation":-76.24},{"name":"huai9","parent":"huaizi","length":12.82,"x":52,"y":20.4,"rotation":99.87},{"name":"zi","parent":"bone","x":2.47,"y":-8.6},{"name":"zi2","parent":"bone","x":2.47,"y":-8.6}],"slots":[{"name":"huaizi","bone":"huaizi","attachment":"huaizi"},{"name":"huai1","bone":"huai1","attachment":"huai1"},{"name":"huai2","bone":"huai2","attachment":"huai2"},{"name":"huai3","bone":"huai3","attachment":"huai3"},{"name":"huai4","bone":"huai4","attachment":"huai4"},{"name":"huai6","bone":"huai6","attachment":"huai6"},{"name":"huai7","bone":"huai7","attachment":"huai7"},{"name":"huai8","bone":"huai8","attachment":"huai8"},{"name":"huai9","bone":"huai9","attachment":"huai9"},{"name":"gou1","bone":"gou1","attachment":"gou1"},{"name":"zi2","bone":"zi2","blend":"additive"},{"name":"zi","bone":"zi","attachment":"zi"},{"name":"gou2","bone":"gou2","attachment":"gou2","blend":"additive"},{"name":"gou3","bone":"gou3","attachment":"gou2","blend":"additive"}],"skins":{"default":{"gou1":{"gou1":{"x":-2.14,"y":3.9,"scaleY":1.858,"width":154,"height":95}},"gou2":{"gou2":{"x":0.36,"y":0.49,"width":36,"height":35}},"gou3":{"gou2":{"x":0.36,"y":0.49,"width":36,"height":35}},"huai1":{"huai1":{"x":7.98,"y":-1.4,"rotation":-4.51,"width":23,"height":25}},"huai2":{"huai2":{"x":5.2,"y":-2.94,"rotation":-1.19,"width":15,"height":16}},"huai3":{"huai3":{"x":3.22,"y":-0.08,"rotation":-87.95,"width":13,"height":16}},"huai4":{"huai4":{"x":6.06,"y":-2.27,"rotation":28.81,"width":19,"height":22}},"huai6":{"huai6":{"x":7.45,"y":2.25,"rotation":148.32,"width":15,"height":15}},"huai7":{"huai7":{"x":5.28,"y":0.16,"rotation":-94.47,"width":12,"height":17}},"huai8":{"huai8":{"x":4.17,"y":-2.35,"rotation":39.37,"width":24,"height":24}},"huai9":{"huai9":{"x":4.02,"y":0.31,"rotation":-136.74,"width":21,"height":20}},"huaizi":{"huaizi":{"x":82.44,"y":0.16,"rotation":-36.87,"width":149,"height":111}},"zi":{"zi":{"x":6.88,"y":-2.16,"width":119,"height":67}},"zi2":{"zi":{"x":6.88,"y":-2.16,"width":119,"height":67}}}},"animations":{"animation":{"slots":{"gou1":{"attachment":[{"time":0,"name":"gou1"}],"color":[{"time":0,"color":"ffffff00","curve":[0.25,0,0.75,1]},{"time":0.3333,"color":"ffffffff","curve":"stepped"},{"time":2,"color":"ffffffff"}]},"gou2":{"attachment":[{"time":0,"name":"gou2"},{"time":0.3666,"name":"gou2"},{"time":1.3666,"name":"gou2"}],"color":[{"time":0,"color":"ffffff00","curve":"stepped"},{"time":0.3666,"color":"ffffff00","curve":[0.25,0,0.75,1]},{"time":0.8666,"color":"ffffffff","curve":[0.25,0,0.75,1]},{"time":1.3666,"color":"ffffff00","curve":"stepped"},{"time":2,"color":"ffffff00"}]},"gou3":{"attachment":[{"time":0,"name":"gou2"},{"time":0.9333,"name":"gou2"},{"time":1.9333,"name":"gou2"}],"color":[{"time":0,"color":"ffffff00","curve":"stepped"},{"time":0.9333,"color":"ffffff00","curve":[0.25,0,0.75,1]},{"time":1.4333,"color":"ffffffff","curve":[0.25,0,0.75,1]},{"time":1.9333,"color":"ffffff00","curve":"stepped"},{"time":2,"color":"ffffff00"}]},"huai1":{"attachment":[{"time":0,"name":null},{"time":0.1666,"name":"huai1"},{"time":0.3,"name":"huai1"},{"time":0.4333,"name":"huai1"},{"time":0.5666,"name":"huai1"}],"color":[{"time":0,"color":"ffffffff","curve":"stepped"},{"time":0.1666,"color":"ffffffff","curve":"stepped"},{"time":0.3,"color":"ffffffff","curve":"stepped"},{"time":0.4333,"color":"ffffffff","curve":"stepped"},{"time":0.5666,"color":"ffffffff","curve":"stepped"},{"time":2,"color":"ffffffff"}]},"huai2":{"attachment":[{"time":0,"name":null},{"time":0.5,"name":"huai2"},{"time":0.6333,"name":"huai2"},{"time":0.7666,"name":"huai2"},{"time":0.9,"name":"huai2"}],"color":[{"time":0,"color":"ffffffff","curve":"stepped"},{"time":0.5,"color":"ffffffff","curve":"stepped"},{"time":0.6333,"color":"ffffffff","curve":"stepped"},{"time":0.7666,"color":"ffffffff","curve":"stepped"},{"time":0.9,"color":"ffffffff","curve":"stepped"},{"time":2,"color":"ffffffff"}]},"huai3":{"attachment":[{"time":0,"name":null},{"time":0.4666,"name":"huai3"},{"time":0.6,"name":"huai3"},{"time":0.7333,"name":"huai3"},{"time":0.8666,"name":"huai3"}],"color":[{"time":0,"color":"ffffffff","curve":"stepped"},{"time":0.4666,"color":"ffffffff","curve":"stepped"},{"time":0.6,"color":"ffffffff","curve":"stepped"},{"time":0.7333,"color":"ffffffff","curve":"stepped"},{"time":0.8666,"color":"ffffffff","curve":"stepped"},{"time":2,"color":"ffffffff"}]},"huai4":{"attachment":[{"time":0,"name":null},{"time":0.3,"name":"huai4"},{"time":0.4333,"name":"huai4"},{"time":0.5666,"name":"huai4"},{"time":0.7,"name":"huai4"}],"color":[{"time":0,"color":"ffffffff","curve":"stepped"},{"time":0.3,"color":"ffffffff","curve":"stepped"},{"time":0.4333,"color":"ffffffff","curve":"stepped"},{"time":0.5666,"color":"ffffffff","curve":"stepped"},{"time":0.7,"color":"ffffffff","curve":"stepped"},{"time":2,"color":"ffffffff"}]},"huai6":{"attachment":[{"time":0,"name":null},{"time":0.3666,"name":"huai6"},{"time":0.5,"name":"huai6"},{"time":0.6333,"name":"huai6"},{"time":0.7666,"name":"huai6"}],"color":[{"time":0,"color":"ffffffff","curve":"stepped"},{"time":0.3666,"color":"ffffffff","curve":"stepped"},{"time":0.5,"color":"ffffffff","curve":"stepped"},{"time":0.6333,"color":"ffffffff","curve":"stepped"},{"time":0.7666,"color":"ffffffff","curve":"stepped"},{"time":2,"color":"ffffffff"}]},"huai7":{"attachment":[{"time":0,"name":null},{"time":0.6666,"name":"huai7"},{"time":0.8,"name":"huai7"},{"time":0.9333,"name":"huai7"},{"time":1.0666,"name":"huai7"}],"color":[{"time":0,"color":"ffffffff","curve":"stepped"},{"time":0.6666,"color":"ffffffff","curve":"stepped"},{"time":0.8,"color":"ffffffff","curve":"stepped"},{"time":0.9333,"color":"ffffffff","curve":"stepped"},{"time":1.0666,"color":"ffffffff","curve":"stepped"},{"time":2,"color":"ffffffff"}]},"huai8":{"attachment":[{"time":0,"name":null},{"time":0.0666,"name":null},{"time":0.3666,"name":"huai8"},{"time":0.5,"name":"huai8"},{"time":0.6333,"name":"huai8"},{"time":0.7666,"name":"huai8"}],"color":[{"time":0,"color":"ffffffff","curve":"stepped"},{"time":0.3666,"color":"ffffffff","curve":"stepped"},{"time":0.5,"color":"ffffffff","curve":"stepped"},{"time":0.6333,"color":"ffffffff","curve":"stepped"},{"time":0.7666,"color":"ffffffff","curve":"stepped"},{"time":2,"color":"ffffffff"}]},"huai9":{"attachment":[{"time":0,"name":null},{"time":0.2333,"name":"huai9"},{"time":0.3666,"name":"huai9"},{"time":0.5,"name":"huai9"},{"time":0.6333,"name":"huai9"}],"color":[{"time":0,"color":"ffffffff","curve":"stepped"},{"time":0.2333,"color":"ffffffff","curve":"stepped"},{"time":0.3666,"color":"ffffffff","curve":"stepped"},{"time":0.5,"color":"ffffffff","curve":"stepped"},{"time":0.6333,"color":"ffffffff","curve":"stepped"},{"time":2,"color":"ffffffff"}]},"huaizi":{"attachment":[{"time":0,"name":null},{"time":0.1,"name":"huaizi"},{"time":0.2333,"name":"huaizi"},{"time":0.4,"name":"huaizi"},{"time":0.5666,"name":"huaizi"}],"color":[{"time":0,"color":"ffffffff","curve":"stepped"},{"time":0.1,"color":"ffffffff","curve":"stepped"},{"time":0.2333,"color":"ffffffff","curve":"stepped"},{"time":0.4,"color":"ffffffff","curve":"stepped"},{"time":0.5666,"color":"ffffffff","curve":"stepped"},{"time":2,"color":"ffffffff"}]},"zi":{"attachment":[{"time":0,"name":null},{"time":0.0333,"name":"zi"},{"time":0.1,"name":"zi"},{"time":0.2333,"name":"zi"},{"time":0.3666,"name":"zi"},{"time":0.5,"name":"zi"},{"time":2,"name":"zi"}],"color":[{"time":0,"color":"ffffffff","curve":"stepped"},{"time":0.1,"color":"ffffffff","curve":"stepped"},{"time":0.2333,"color":"ffffffff","curve":"stepped"},{"time":0.3666,"color":"ffffffff","curve":"stepped"},{"time":0.5,"color":"ffffffff","curve":"stepped"},{"time":2,"color":"ffffffff"}]},"zi2":{"attachment":[{"time":0,"name":null},{"time":0.1666,"name":"zi"},{"time":0.3,"name":"zi"}],"color":[{"time":0,"color":"ffffffff","curve":"stepped"},{"time":0.1666,"color":"ffffffff","curve":[0.25,0,0.75,1]},{"time":0.3,"color":"ffffff52","curve":[0.25,0,0.75,1]},{"time":0.5333,"color":"ffffff00","curve":"stepped"},{"time":2,"color":"ffffff00"}]}},"bones":{"gou1":{"rotate":[{"time":0,"angle":0,"curve":[0.25,0,0.75,1]},{"time":1.1666,"angle":90}],"translate":[{"time":0,"x":0,"y":0}],"scale":[{"time":0,"x":1,"y":1}]},"gou2":{"rotate":[{"time":0,"angle":0,"curve":"stepped"},{"time":0.3666,"angle":0,"curve":[0.25,0,0.75,1]},{"time":1.3666,"angle":-92.34}],"translate":[{"time":0,"x":0,"y":0,"curve":"stepped"},{"time":0.3666,"x":0,"y":0,"curve":"stepped"},{"time":1.3666,"x":0,"y":0}],"scale":[{"time":0,"x":0.4,"y":0.4,"curve":"stepped"},{"time":0.3666,"x":0.4,"y":0.4,"curve":[0.25,0,0.75,1]},{"time":0.8666,"x":1.243,"y":1.243,"curve":[0.25,0,0.75,1]},{"time":1.3666,"x":0.481,"y":0.481}]},"gou3":{"rotate":[{"time":0,"angle":0,"curve":"stepped"},{"time":0.9333,"angle":0,"curve":[0.25,0,0.75,1]},{"time":1.9333,"angle":-92.34}],"translate":[{"time":0,"x":0,"y":0,"curve":"stepped"},{"time":0.9333,"x":0,"y":0,"curve":"stepped"},{"time":1.9333,"x":0,"y":0}],"scale":[{"time":0,"x":0.4,"y":0.4,"curve":"stepped"},{"time":0.9333,"x":0.4,"y":0.4,"curve":[0.25,0,0.75,1]},{"time":1.4333,"x":1.243,"y":1.243,"curve":[0.25,0,0.75,1]},{"time":1.9333,"x":0.481,"y":0.481}]},"huai1":{"rotate":[{"time":0,"angle":0,"curve":[0.25,0,0.75,1]},{"time":0.1666,"angle":-29.87,"curve":[0.25,0,0.75,1]},{"time":0.3,"angle":14.23,"curve":[0.25,0,0.75,1]},{"time":0.4333,"angle":-6.55,"curve":[0.25,0,0.75,1]},{"time":0.5666,"angle":0}],"translate":[{"time":0,"x":0,"y":0,"curve":"stepped"},{"time":0.1666,"x":0,"y":0,"curve":"stepped"},{"time":0.3,"x":0,"y":0,"curve":"stepped"},{"time":0.4333,"x":0,"y":0,"curve":"stepped"},{"time":0.5666,"x":0,"y":0}],"scale":[{"time":0,"x":1,"y":1,"curve":[0.25,0,0.75,1]},{"time":0.1666,"x":0.46,"y":0.46,"curve":[0.25,0,0.75,1]},{"time":0.3,"x":1,"y":1,"curve":"stepped"},{"time":0.4333,"x":1,"y":1,"curve":"stepped"},{"time":0.5666,"x":1,"y":1}]},"huai2":{"rotate":[{"time":0,"angle":0,"curve":[0.25,0,0.75,1]},{"time":0.5,"angle":-69.29,"curve":[0.25,0,0.75,1]},{"time":0.6333,"angle":15.92,"curve":[0.25,0,0.75,1]},{"time":0.7666,"angle":-13.29,"curve":[0.25,0,0.75,1]},{"time":0.9,"angle":0}],"translate":[{"time":0,"x":0,"y":0,"curve":"stepped"},{"time":0.5,"x":0,"y":0,"curve":"stepped"},{"time":0.6333,"x":0,"y":0,"curve":"stepped"},{"time":0.7666,"x":0,"y":0,"curve":"stepped"},{"time":0.9,"x":0,"y":0}],"scale":[{"time":0,"x":1,"y":1,"curve":[0.25,0,0.75,1]},{"time":0.5,"x":0.495,"y":0.495,"curve":[0.25,0,0.75,1]},{"time":0.6333,"x":1,"y":1,"curve":"stepped"},{"time":0.7666,"x":1,"y":1,"curve":"stepped"},{"time":0.9,"x":1,"y":1}]},"huai3":{"rotate":[{"time":0,"angle":0,"curve":[0.25,0,0.75,1]},{"time":0.4666,"angle":-27.25,"curve":[0.25,0,0.75,1]},{"time":0.6,"angle":28.36,"curve":[0.25,0,0.75,1]},{"time":0.7333,"angle":-4.84,"curve":[0.25,0,0.75,1]},{"time":0.8666,"angle":0}],"translate":[{"time":0,"x":0,"y":0,"curve":"stepped"},{"time":0.4666,"x":0,"y":0,"curve":"stepped"},{"time":0.6,"x":0,"y":0,"curve":"stepped"},{"time":0.7333,"x":0,"y":0,"curve":"stepped"},{"time":0.8666,"x":0,"y":0}],"scale":[{"time":0,"x":1,"y":1,"curve":[0.25,0,0.75,1]},{"time":0.4666,"x":0.528,"y":0.528,"curve":[0.25,0,0.75,1]},{"time":0.6,"x":1,"y":1,"curve":"stepped"},{"time":0.7333,"x":1,"y":1,"curve":"stepped"},{"time":0.8666,"x":1,"y":1}]},"huai4":{"rotate":[{"time":0,"angle":0,"curve":[0.25,0,0.75,1]},{"time":0.3,"angle":18.08,"curve":[0.25,0,0.75,1]},{"time":0.4333,"angle":-15.32,"curve":[0.25,0,0.75,1]},{"time":0.5666,"angle":3.12,"curve":[0.25,0,0.75,1]},{"time":0.7,"angle":0}],"translate":[{"time":0,"x":0,"y":0,"curve":"stepped"},{"time":0.3,"x":0,"y":0,"curve":"stepped"},{"time":0.4333,"x":0,"y":0,"curve":"stepped"},{"time":0.5666,"x":0,"y":0,"curve":"stepped"},{"time":0.7,"x":0,"y":0}],"scale":[{"time":0,"x":1,"y":1,"curve":[0.25,0,0.75,1]},{"time":0.3,"x":0.473,"y":0.473,"curve":[0.25,0,0.75,1]},{"time":0.4333,"x":1,"y":1,"curve":"stepped"},{"time":0.5666,"x":1,"y":1,"curve":"stepped"},{"time":0.7,"x":1,"y":1}]},"huai6":{"rotate":[{"time":0,"angle":0,"curve":[0.25,0,0.75,1]},{"time":0.3666,"angle":-42.77,"curve":[0.25,0,0.75,1]},{"time":0.5,"angle":-341.77,"curve":[0.25,0,0.75,1]},{"time":0.6333,"angle":-8.18,"curve":[0.25,0,0.75,1]},{"time":0.7666,"angle":0}],"translate":[{"time":0,"x":0,"y":0,"curve":"stepped"},{"time":0.3666,"x":0,"y":0,"curve":"stepped"},{"time":0.5,"x":0,"y":0,"curve":"stepped"},{"time":0.6333,"x":0,"y":0,"curve":"stepped"},{"time":0.7666,"x":0,"y":0}],"scale":[{"time":0,"x":1,"y":1,"curve":[0.25,0,0.75,1]},{"time":0.3666,"x":0.474,"y":0.474,"curve":[0.25,0,0.75,1]},{"time":0.5,"x":1,"y":1,"curve":"stepped"},{"time":0.6333,"x":1,"y":1,"curve":"stepped"},{"time":0.7666,"x":1,"y":1}]},"huai7":{"rotate":[{"time":0,"angle":0,"curve":[0.25,0,0.75,1]},{"time":0.6666,"angle":-24.48,"curve":[0.25,0,0.75,1]},{"time":0.8,"angle":16.7,"curve":[0.25,0,0.75,1]},{"time":0.9333,"angle":-7.7,"curve":[0.25,0,0.75,1]},{"time":1.0666,"angle":0}],"translate":[{"time":0,"x":0,"y":0,"curve":"stepped"},{"time":0.6666,"x":0,"y":0,"curve":"stepped"},{"time":0.8,"x":0,"y":0,"curve":"stepped"},{"time":0.9333,"x":0,"y":0,"curve":"stepped"},{"time":1.0666,"x":0,"y":0}],"scale":[{"time":0,"x":1,"y":1,"curve":[0.25,0,0.75,1]},{"time":0.6666,"x":0.503,"y":0.503,"curve":[0.25,0,0.75,1]},{"time":0.8,"x":1,"y":1,"curve":"stepped"},{"time":0.9333,"x":1,"y":1,"curve":"stepped"},{"time":1.0666,"x":1,"y":1}]},"huai8":{"rotate":[{"time":0,"angle":0,"curve":[0.25,0,0.75,1]},{"time":0.3666,"angle":-21.02,"curve":[0.25,0,0.75,1]},{"time":0.5,"angle":15.55,"curve":[0.25,0,0.75,1]},{"time":0.6333,"angle":-7.89,"curve":[0.25,0,0.75,1]},{"time":0.7666,"angle":0}],"translate":[{"time":0,"x":0,"y":0,"curve":"stepped"},{"time":0.3666,"x":0,"y":0,"curve":"stepped"},{"time":0.5,"x":0,"y":0,"curve":"stepped"},{"time":0.6333,"x":0,"y":0,"curve":"stepped"},{"time":0.7666,"x":0,"y":0}],"scale":[{"time":0,"x":1,"y":1,"curve":[0.25,0,0.75,1]},{"time":0.3666,"x":0.351,"y":0.351,"curve":[0.25,0,0.75,1]},{"time":0.5,"x":1,"y":1,"curve":"stepped"},{"time":0.6333,"x":1,"y":1,"curve":"stepped"},{"time":0.7666,"x":1,"y":1}]},"huai9":{"rotate":[{"time":0,"angle":0,"curve":[0.25,0,0.75,1]},{"time":0.2333,"angle":-29.18,"curve":[0.25,0,0.75,1]},{"time":0.3666,"angle":11.07,"curve":[0.25,0,0.75,1]},{"time":0.5,"angle":-6.35,"curve":[0.25,0,0.75,1]},{"time":0.6333,"angle":0}],"translate":[{"time":0,"x":0,"y":0,"curve":"stepped"},{"time":0.2333,"x":0,"y":0,"curve":"stepped"},{"time":0.3666,"x":0,"y":0,"curve":"stepped"},{"time":0.5,"x":0,"y":0,"curve":"stepped"},{"time":0.6333,"x":0,"y":0}],"scale":[{"time":0,"x":1,"y":1,"curve":[0.25,0,0.75,1]},{"time":0.2333,"x":0.491,"y":0.491,"curve":[0.25,0,0.75,1]},{"time":0.3666,"x":1,"y":1,"curve":"stepped"},{"time":0.5,"x":1,"y":1,"curve":"stepped"},{"time":0.6333,"x":1,"y":1}]},"huaizi":{"rotate":[{"time":0,"angle":0,"curve":"stepped"},{"time":0.1,"angle":0,"curve":[0.25,0,0.75,1]},{"time":0.2333,"angle":6.6,"curve":[0.25,0,0.75,1]},{"time":0.4,"angle":-1.75,"curve":[0.25,0,0.75,1]},{"time":0.5666,"angle":0,"curve":[0.25,0,0.75,1]},{"time":1.4333,"angle":2.15}],"translate":[{"time":0,"x":0,"y":0,"curve":"stepped"},{"time":0.1,"x":0,"y":0,"curve":"stepped"},{"time":0.2333,"x":0,"y":0,"curve":"stepped"},{"time":0.4,"x":0,"y":0,"curve":"stepped"},{"time":0.5666,"x":0,"y":0}],"scale":[{"time":0,"x":1,"y":1,"curve":[0.25,0,0.75,1]},{"time":0.1,"x":0.255,"y":0.255,"curve":[0.25,0,0.75,1]},{"time":0.2333,"x":1,"y":1,"curve":"stepped"},{"time":0.4,"x":1,"y":1,"curve":"stepped"},{"time":0.5666,"x":1,"y":1}]},"zi":{"rotate":[{"time":0,"angle":0,"curve":"stepped"},{"time":0.1,"angle":0,"curve":"stepped"},{"time":0.2333,"angle":0,"curve":"stepped"},{"time":0.3666,"angle":0,"curve":"stepped"},{"time":0.5,"angle":0,"curve":"stepped"},{"time":2,"angle":0}],"translate":[{"time":0,"x":0,"y":0,"curve":"stepped"},{"time":0.1,"x":0,"y":0,"curve":"stepped"},{"time":0.2333,"x":0,"y":0,"curve":"stepped"},{"time":0.3666,"x":0,"y":0,"curve":"stepped"},{"time":0.5,"x":0,"y":0,"curve":"stepped"},{"time":2,"x":0,"y":0}],"scale":[{"time":0,"x":0.318,"y":0.318,"curve":[0.25,0,0.75,1]},{"time":0.1,"x":1.851,"y":1.851,"curve":[0.25,0,0.75,1]},{"time":0.2333,"x":0.812,"y":0.812,"curve":[0.25,0,0.75,1]},{"time":0.3666,"x":1.083,"y":1.083,"curve":[0.25,0,0.75,1]},{"time":0.5,"x":1,"y":1,"curve":"stepped"},{"time":2,"x":1,"y":1}]},"zi2":{"rotate":[{"time":0,"angle":0,"curve":"stepped"},{"time":0.1666,"angle":0}],"translate":[{"time":0,"x":0,"y":0,"curve":"stepped"},{"time":0.1666,"x":0,"y":0}],"scale":[{"time":0,"x":1,"y":1,"curve":[0.25,0,0.75,1]},{"time":0.1666,"x":1.179,"y":1.179,"curve":[0.25,0,0.75,1]},{"time":0.3,"x":1.447,"y":1.447,"curve":[0.25,0,0.75,1]},{"time":0.5333,"x":1.574,"y":1.574}]},"root":{"rotate":[{"time":0,"angle":0}],"translate":[{"time":0,"x":0,"y":0}],"scale":[{"time":0,"x":1,"y":1}]},"bone":{"rotate":[{"time":0,"angle":0}],"translate":[{"time":0,"x":0,"y":0}],"scale":[{"time":0,"x":1,"y":1}]}},"drawOrder":[{"time":0},{"time":0.1},{"time":0.1666},{"time":0.3},{"time":0.3666},{"time":0.4333},{"time":0.4666},{"time":0.5},{"time":0.5666},{"time":0.6},{"time":0.6333},{"time":0.6666},{"time":0.7333},{"time":0.7666},{"time":0.8},{"time":0.8666},{"time":0.9},{"time":0.9333},{"time":1.0666},{"time":1.4666},{"time":1.7},{"time":1.8},{"time":1.8666},{"time":2},{"time":2.1},{"time":2.3}]}}}